ichier/__init__.py
ichier/__main__.py
ichier/_main.py
ichier/errors.py
ichier/release.py
ichier/node/__init__.py
ichier/node/design.py
ichier/node/fig.py
ichier/node/instance.py
ichier/node/module.py
ichier/node/net.py
ichier/node/obj.py
ichier/node/parameter.py
ichier/node/reference.py
ichier/node/terminal.py
ichier/node/trace.py
ichier/parser/__init__.py
ichier/parser/spice/__init__.py
ichier/parser/spice/p_inst.py
ichier/parser/spice/parser.py
ichier/parser/spice/string.py
ichier/parser/verilog/__init__.py
ichier/parser/verilog/lexer.py
ichier/parser/verilog/parser.py
ichier/utils/__init__.py
ichier/utils/escape.py
ichier/utils/progress.py
ichier/utils/name_parse/__init__.py
ichier/utils/name_parse/lexer.py
ichier/utils/name_parse/parser.py
ichier-0.2.7.dist-info/LICENSE
ichier-0.2.7.dist-info/METADATA
ichier-0.2.7.dist-info/WHEEL
ichier-0.2.7.dist-info/entry_points.txt
ichier-0.2.7.dist-info/top_level.txt
ichier-0.2.7.dist-info/RECORD
