Metadata-Version: 2.1
Name: ichier
Version: 0.2.7
Summary: Integrated Circuit Hierarchy
Home-page: https://github.com/yeungchie/ichier
Author: YEUNGCHIE
Author-email: im.yeung.chie@outlook.com
Keywords: ichier,verilog,spice,cdl,ic,hierarchy,linux
Classifier: Development Status :: 3 - Alpha
Classifier: Intended Audience :: Developers
Classifier: Programming Language :: Python :: 3
Classifier: Programming Language :: Python :: 3.8
Classifier: Programming Language :: Python :: 3.12
Classifier: License :: OSI Approved :: GNU Affero General Public License v3
Classifier: Operating System :: Unix
Requires-Python: >=3.8
License-File: LICENSE
Requires-Dist: icutk>=0.3.7
Requires-Dist: ply>=3.11
Provides-Extra: full
Requires-Dist: ipython; extra == "full"
Requires-Dist: rich; extra == "full"
